Workbook

Sheet Name
B4: Student Name | C4: Student ID
B5: Kush Anand Shah | C5: a1945524
B6: Supriya Abhijit Pingle | C6: a1944342
B7: Alan Sam Alelil | C7: a1930481
B8: Harikrishnan Manoj | C8: a1949187
B9: Chinmay Shetty | C9: a1916150
B10: Randeep Ravindra Pawar | C10: a1911485
B12: Sum ID | C12: 9681019

Sheet Income Sheet
B1: 2024 | C1: 2023 | D1: 2022 | E1: 2021 | F1: 2020 | H1: 2024 Adjusted | I1: 2023 Adjusted | J1: 2022 Adjusted | K1: 2021 Adjusted | L1: 2020 Adjusted | N1: 2024 (% Rev) | O1: 2023 (% Rev) | P1: 2022 (% Rev) | Q1: 2021 (% Rev) | R1: 2020 (% Rev) | S1: Average | U1: 2025 F | V1: 2026 F | W1: 2027 F | X1: 2028 F | Y1: 2029 F
A2: INCOME STATEMENT | H2: No adjustments for Income Statement
A3: Operating Revenue | B3: 8967.41 | C3: 8168.95 | D3: 9340.15 | E3: 8754.12 | F3: 6831.84 | N3: =B4/B3 -> 0.90387637 | O3: =C4/C3 -> 0.87524712 | P3: =D4/D3 -> 0.76870072 | Q3: =E4/E3 -> 0.78047708 | R3: =F4/F3 -> 0.88084616 | S3: =AVERAGE(N3:R4) -> 0.84182949 | U3: =Regression!L27 -> 9948.5409 | V3: =Regression!L28 -> 10340.633 | W3: =Regression!L29 -> 10868.869 | X3: =Regression!L30 -> 11328.863 | Y3: =Regression!L31 -> 11742.246
A4: Operating Expenses | B4: 8105.43 | C4: 7149.85 | D4: 7179.78 | E4: 6832.39 | F4: 6017.8 | U4: =U3*$S$3 -> 8374.9751 | V4: =V3*$S$3 -> 8705.0499 | W4: =W3*$S$3 -> 9149.7343 | X4: =X3*$S$3 -> 9536.9712 | Y4: =Y3*$S$3 -> 9884.9686
A5: EBITDA | B5: 861.97 | C5: 1019.1 | D5: 2160.37 | E5: 1921.73 | F5: 814.05 | U5: =U3-U4 -> 1573.5658 | V5: =V3-V4 -> 1635.5832 | W5: =W3-W4 -> 1719.1345 | X5: =X3-X4 -> 1791.8921 | Y5: =Y3-Y4 -> 1857.277
A6: Amortization | B6: 82.92 | C6: 71.63 | D6: 67.99 | E6: 68.2 | F6: 65.21 | N6: =B6/B3 -> 0.0092468171 | O6: =C6/C3 -> 0.0087685688 | P6: =D6/D3 -> 0.0072793263 | Q6: =E6/E3 -> 0.0077906174 | R6: =F6/F3 -> 0.0095450128 | S6: =AVERAGE(N6:R6) -> 0.0085260685 | U6: =U3*$S$6 -> 84.821941 | V6: =V3*$S$6 -> 88.164946 | W6: =W3*$S$6 -> 92.66872 | X6: =X3*$S$6 -> 96.590664 | Y6: =Y3*$S$6 -> 100.11519
A7: Depriciation | B7: 694.39 | C7: 631.3 | D7: 607.43 | E7: 573.39 | F7: 540.66 | N7: =B7/B4 -> 0.08566973 | O7: =C7/C4 -> 0.088295559 | P7: =D7/D4 -> 0.084602871 | Q7: =E7/E4 -> 0.083922317 | R7: =F7/F4 -> 0.089843464 | S7: =AVERAGE(N7:R7) -> 0.086466788 | U7: =$S$7*H33 -> 263.88626 | V7: =$S$7*U33 -> 287.09605 | W7: =$S$7*V33 -> 298.41109 | X7: =$S$7*W33 -> 313.65497 | Y7: =$S$7*X33 -> 326.92954
A8: Operating Profit
A9: EBIT | B9: =B5-(B6+C7) -> 147.75 | C9: =C5-(C6+D7) -> 340.04 | D9: =D5-(D6+E7) -> 1518.99 | E9: =E5-(E6+F7) -> 1312.87 | F9: =F5-(F6+G7) -> 748.84 | U9: =U5-(U6+U7) -> 1224.8576 | V9: =V5-(V6+V7) -> 1260.3222 | W9: =W5-(W6+W7) -> 1328.0547 | X9: =X5-(X6+X7) -> 1381.6465 | Y9: =Y5-(Y6+Y7) -> 1430.2322
A10: Non-Operating Expenses
A11: Interest Expense | B11: 151.35 | C11: 87.02 | D11: 79.82 | E11: 92.52 | F11: 112.85 | N11: =B11/B3 -> 0.016877783 | O11: =C11/C3 -> 0.010652532 | P11: =D11/D3 -> 0.0085459013 | Q11: =E11/E3 -> 0.010568738 | R11: =F11/F3 -> 0.016518244 | S11: =AVERAGE(N11:R11) -> 0.01263264 | U11: =U$3*$S11 -> 125.67633 | V11: =V$3*$S11 -> 130.62949 | W11: =W$3*$S11 -> 137.3025 | X11: =X$3*$S11 -> 143.11345 | Y11: =Y$3*$S11 -> 148.33556
A12: Non-Recurring Adjustments - Non-Operating- Decrease/(Increase) | E12: 5.09 | F12: 11.09 | N12: =B12/B3 -> 0 | O12: =C12/C3 -> 0 | P12: =D12/D3 -> 0 | Q12: =E12/E3 -> 0.00058144051 | R12: =F12/F3 -> 0.0016232816 | S12: =AVERAGE(N12:R12) -> 0.00044094442 | U12: =U$3*$S12 -> 4.3867536 | V12: =V$3*$S12 -> 4.5596444 | W12: =W$3*$S12 -> 4.792567 | X12: =X$3*$S12 -> 4.995399 | Y12: =Y$3*$S12 -> 5.1776776
A13: Normalized Pre-tax Profit | B13: =B5-SUM(B11:B12) -> 710.62 | C13: 932.07 | D13: 2080.55 | E13: 1834.3 | F13: 712.29 | U13: =U5-SUM(U11:U12) -> 1443.5027 | V13: =V5-SUM(V11:V12) -> 1500.3941 | W13: =W5-SUM(W11:W12) -> 1577.0395 | X13: =X5-SUM(X11:X12) -> 1643.7832 | Y13: =Y5-SUM(Y11:Y12) -> 1703.7637
A14: Taxes
A15: Income Taxes | B15: 186.85 | C15: 223.26 | D15: 561.74 | E15: 480.94 | F15: 157.16 | N15: =B15/B13 -> 0.26293941 | O15: =C15/C13 -> 0.23953137 | P15: =D15/D13 -> 0.26999591 | Q15: =E15/E13 -> 0.26219266 | R15: =F15/F13 -> 0.22064047 | S15: =AVERAGE(N15:R15) -> 0.25105996 | U15: =U13*$S$15 -> 362.40574 | V15: =V13*$S$15 -> 376.68889 | W15: =W13*$S$15 -> 395.93147 | X15: =X13*$S$15 -> 412.68816 | Y15: =Y13*$S$15 -> 427.74686
A16: Net Income After Tax
A17: Net Income after Tax | B17: 543.8 | C17: 707.93 | D17: 1515.47 | E17: 1347.66 | F17: 541.9 | N17: =B17/B3 -> 0.060641813 | O17: =C17/C3 -> 0.086661076 | P17: =D17/D3 -> 0.16225328 | Q17: =E17/E3 -> 0.1539458 | R17: =F17/F3 -> 0.079319773 | S17: =AVERAGE(N17:R17) -> 0.10856435 | U17: =U13-U15 -> 1081.097 | V17: =V13-V15 -> 1123.7052 | W17: =W13-W15 -> 1181.108 | X17: =X13-X15 -> 1231.0951 | Y17: =Y13-Y15 -> 1276.0169
A18: After Tax Income/Expense
A19: Minority Interest | B19: 32.71 | C19: 22.95 | D19: 54.9 | E19: 32.62 | F19: 14.15 | N19: =B19/B3 -> 0.003647653 | O19: =C19/C3 -> 0.0028094186 | P19: =D19/D3 -> 0.0058778499 | Q19: =E19/E3 -> 0.0037262455 | R19: =F19/F3 -> 0.0020711843 | S19: =AVERAGE(N19:R19) -> 0.0036264703 | U19: =U3*$S$19 -> 36.078088 | V19: =V3*$S$19 -> 37.499999 | W19: =W3*$S$19 -> 39.41563 | X19: =X3*$S$19 -> 41.083786 | Y19: =Y3*$S$19 -> 42.582904
A20: Net Income | B20: 511.09 | C20: 684.98 | D20: 1460.57 | E20: 1315.04 | F20: 527.75 | N20: =B20/B3 -> 0.05699416 | O20: =C20/C3 -> 0.083851658 | P20: =D20/D3 -> 0.15637543 | Q20: =E20/E3 -> 0.15021955 | R20: =F20/F3 -> 0.077248589 | S20: =AVERAGE(N20:R20) -> 0.10493788 | U20: =U17+U19 -> 1117.1751 | V20: =V17+V19 -> 1161.2052 | W20: =W17+W19 -> 1220.5236 | X20: =X17+X19 -> 1272.1789 | Y20: =Y17+Y19 -> 1318.5998
A22: Balance sheet | H22: 2024 Adjusted | I22: 2023 Adjusted | J22: 2022 Adjusted | K22: 2021 Adjusted | L22: 2020 Adjusted | N22: 2024 (% Rev) | O22: 2023 (% Rev) | P22: 2022 (% Rev) | Q22: 2021 (% Rev) | R22: 2020 (% Rev) | S22: Average
A23: Current Assets
A24: Cash & Cash Equivalents | B24: 645 | C24: 797.99 | D24: 780 | E24: 899.83 | F24: 1230.15 | H24: 645 | I24: 797.99 | J24: 780 | K24: 899.83 | L24: 1230.15 | N24: =H24/$B$4 -> 0.079576284 | O24: =I24/$B$4 -> 0.098451285 | P24: =J24/$B$4 -> 0.096231785 | Q24: =K24/$B$4 -> 0.1110157 | R24: =L24/$B$4 -> 0.15176863 | S24: =AVERAGE(N24:R24) -> 0.10740874 | U24: =U54+U62-U38-U32-U31-U34 -> 2694.5166 | V24: =V54+V62-V38-V32-V31-V34 -> 2800.713 | W24: =W54+W62-W38-W32-W31-W34 -> 2943.7832 | X24: =X54+X62-X38-X32-X31-X34 -> 3068.3706 | Y24: =Y54+Y62-Y38-Y32-Y31-Y34 -> 3180.3333
A25: Loans & Receivables - Net - Short-Term | B25: 1362.18 | C25: 1022.18 | D25: 1217.46 | E25: 1088.72 | F25: 986.77 | H25: 1362.18 | I25: 1022.18 | J25: 1217.46 | K25: 1088.72 | L25: 986.77 | N25: =H25/$B$4 -> 0.16805771 | O25: =I25/$B$4 -> 0.12611052 | P25: =J25/$B$4 -> 0.15020301 | Q25: =K25/$B$4 -> 0.13431983 | R25: =L25/$B$4 -> 0.12174184 | S25: =AVERAGE(N25:R25) -> 0.14008658 | U25: =U3*$S$25 -> 1393.6571 | V25: =V3*$S$25 -> 1448.584 | W25: =W3*$S$25 -> 1522.5827 | X25: =X3*$S$25 -> 1587.0218 | Y25: =Y3*$S$25 -> 1644.9311
A26: Trade Accounts & Trade Notes Receivable - Net | B26: 910.89 | C26: 770.96 | D26: 930.94 | E26: 846.36 | F26: 713.74 | H26: 910.89 | I26: 770.96 | J26: 930.94 | K26: 846.36 | L26: 713.74 | N26: =H26/$B$4 -> 0.11238022 | O26: =I26/$B$4 -> 0.095116484 | P26: =J26/$B$4 -> 0.11485387 | Q26: =K26/$B$4 -> 0.10441889 | R26: =L26/$B$4 -> 0.088057019 | S26: =AVERAGE(N26:R26) -> 0.1029653 | U26: =U3*$S$26 -> 1024.3545 | V26: =V3*$S$26 -> 1064.7264 | W26: =W3*$S$26 -> 1119.1163 | X26: =X3*$S$26 -> 1166.4798 | Y26: =Y3*$S$26 -> 1209.0438
A27: Provision - Trade Accounts & Trade Notes Receivable | B27: 154.84 | C27: 171 | D27: 174.37 | E27: 191.57 | F27: 145.49 | H27: 154.84 | I27: 171 | J27: 174.37 | K27: 191.57 | L27: 145.49 | N27: =H27/$B$4 -> 0.019103243 | O27: =I27/$B$4 -> 0.021096968 | P27: =J27/$B$4 -> 0.021512739 | Q27: =K27/$B$4 -> 0.023634773 | R27: =L27/$B$4 -> 0.017949695 | S27: =AVERAGE(N27:R27) -> 0.020659484 | U27: =U3*$S$27 -> 205.53172 | V27: =V3*$S$27 -> 213.63214 | W27: =W3*$S$27 -> 224.54522 | X27: =X3*$S$27 -> 234.04847 | Y27: =Y3*$S$27 -> 242.58873
A28: Inventories - Total | B28: 208.83 | C28: 199.2 | D28: 216.19 | E28: 224.39 | F28: 163.43 | H28: 208.83 | I28: 199.2 | J28: 216.19 | K28: 224.39 | L28: 163.43 | N28: =H28/$B$4 -> 0.02576421 | O28: =I28/$B$4 -> 0.024576117 | P28: =J28/$B$4 -> 0.026672243 | Q28: =K28/$B$4 -> 0.027683911 | R28: =L28/$B$4 -> 0.020163027 | S28: =AVERAGE(N28:R28) -> 0.024971902 | U28: =U3*$S$28 -> 248.43398 | V28: =V3*$S$28 -> 258.22527 | W28: =W3*$S$28 -> 271.41632 | X28: =X3*$S$28 -> 282.90326 | Y28: =Y3*$S$28 -> 293.2262
A29: Total Current Assets | B29: =SUM(B24:B28) -> 3281.74 | C29: =SUM(C24:C28) -> 2961.33 | D29: =SUM(D24:D28) -> 3318.96 | E29: =SUM(E24:E28) -> 3250.87 | F29: =SUM(F24:F28) -> 3239.58 | H29: =SUM(H24:H28) -> 3281.74 | I29: =SUM(I24:I28) -> 2961.33 | J29: =SUM(J24:J28) -> 3318.96 | K29: =SUM(K24:K28) -> 3250.87 | L29: =SUM(L24:L28) -> 3239.58 | U29: =SUM(U24:U28) -> 5566.4939 | V29: =SUM(V24:V28) -> 5785.8807 | W29: =SUM(W24:W28) -> 6081.4438 | X29: =SUM(X24:X28) -> 6338.8238 | Y29: =SUM(Y24:Y28) -> 6570.1231
A30: Non-Current Assets
A31: Investments - Long-Term | B31: 198.35 | C31: 175.8 | D31: 145.22 | E31: 108.11 | F31: 91.75 | H31: 198.35 | I31: 175.8 | J31: 145.22 | K31: 108.11 | L31: 91.75 | N31: =H31/$B$4 -> 0.02447125 | O31: =I31/$B$4 -> 0.021689164 | P31: =J31/$B$4 -> 0.017916384 | Q31: =K31/$B$4 -> 0.013337972 | R31: =L31/$B$4 -> 0.011319572 | S31: =AVERAGE(N31:R31) -> 0.017746868 | U31: =U$3*$S31 -> 176.55545 | V31: =V$3*$S31 -> 183.51386 | W31: =W$3*$S31 -> 192.88839 | X31: =X$3*$S31 -> 201.05185 | Y31: =Y$3*$S31 -> 208.38809
A32: Receivables & Loans - Long-Term | B32: 22.24 | C32: 37.74 | D32: 38.19 | E32: 31.55 | F32: 50.43 | H32: 22.24 | I32: 37.74 | J32: 38.19 | K32: 31.55 | L32: 50.43 | N32: =H32/$B$4 -> 0.0027438396 | O32: =I32/$B$4 -> 0.0046561379 | P32: =J32/$B$4 -> 0.0047116563 | Q32: =K32/$B$4 -> 0.0038924523 | R32: =L32/$B$4 -> 0.006221755 | S32: =AVERAGE(N32:R32) -> 0.0044451682 | U32: =U$3*$S32 -> 44.222938 | V32: =V$3*$S32 -> 45.965854 | W32: =W$3*$S32 -> 48.31395 | X32: =X$3*$S32 -> 50.358703 | Y32: =Y$3*$S32 -> 52.196257
A33: PPE | B33: 3051.88 | C33: 2798.11 | D33: 2624.86 | E33: 2552.92 | F33: 2498.08 | H33: 3051.88 | I33: 2798.11 | J33: 2624.86 | K33: 2552.92 | L33: 2498.08 | N33: =H33/$B$4 -> 0.3765229 | O33: =I33/$B$4 -> 0.34521426 | P33: =J33/$B$4 -> 0.3238397 | Q33: =K33/$B$4 -> 0.31496417 | R33: =L33/$B$4 -> 0.30819833 | S33: =AVERAGE(N33:R33) -> 0.33374787 | U33: =U$3*$S33 -> 3320.3043 | V33: =V$3*$S33 -> 3451.1643 | W33: =W$3*$S33 -> 3627.4618 | X33: =X$3*$S33 -> 3780.984 | Y33: =Y$3*$S33 -> 3918.9494
A34: Other Non-Current Assets - Total | B34: 74.75 | C34: 80.19 | D34: 76.34 | E34: 71.58 | F34: 76.86 | H34: 74.75 | I34: 80.19 | J34: 76.34 | K34: 71.58 | L34: 76.86 | N34: =H34/$B$4 -> 0.0092222128 | O34: =I34/$B$4 -> 0.0098933678 | P34: =J34/$B$4 -> 0.0094183776 | Q34: =K34/$B$4 -> 0.0088311169 | R34: =L34/$B$4 -> 0.0094825321 | S34: =AVERAGE(N34:R34) -> 0.0093695214 | U34: =U$3*$S34 -> 93.213067 | V34: =V$3*$S34 -> 96.886784 | W34: =W$3*$S34 -> 101.8361 | X34: =X$3*$S34 -> 106.14603 | Y34: =Y$3*$S34 -> 110.01922
A35: Deferred Tax - Asset - Long-Term | B35: 65.94 | C35: 72.38 | D35: 68.99 | E35: 65.28 | F35: 70.76 | H35: 0 | I35: 0 | J35: 0 | K35: 0 | L35: 0 | N35: =H35/$B$4 -> 0 | O35: =I35/$B$4 -> 0 | P35: =J35/$B$4 -> 0 | Q35: =K35/$B$4 -> 0 | R35: =L35/$B$4 -> 0 | S35: =AVERAGE(N35:R35) -> 0 | U35: 0 | V35: 0 | W35: 0 | X35: 0 | Y35: 0
A36: Goodwill/Cost in Excess of Assets Purchased - Net | B36: 8405.12 | C36: 7237.43 | D36: 6852.96 | E36: 6231.85 | F36: 6486.33 | H36: 8405.12 | I36: 7237.43 | J36: 6852.96 | K36: 6231.85 | L36: 6486.33 | N36: =H36/$B$4 -> 1.036974 | O36: =I36/$B$4 -> 0.8929113 | P36: =J36/$B$4 -> 0.84547766 | Q36: =K36/$B$4 -> 0.76884878 | R36: =L36/$B$4 -> 0.80024502 | S36: =AVERAGE(N36:R36) -> 0.86889135 | U36: =U$3*$S36 -> 8644.2011 | V36: =V$3*$S36 -> 8984.8867 | W36: =W$3*$S36 -> 9443.8661 | X36: =X$3*$S36 -> 9843.5513 | Y36: =Y$3*$S36 -> 10202.736
A37: Intangible Assets - excluding Goodwill - Net - Total | B37: 721.15 | C37: 552.19 | D37: 508.52 | E37: 480.4 | F37: 468.57 | H37: =B37*25% -> 180.2875 | I37: =C37*25% -> 138.0475 | J37: =D37*25% -> 127.13 | K37: =E37*25% -> 120.1 | L37: =F37*25% -> 117.1425 | N37: =H37/$B$4 -> 0.022242805 | O37: =I37/$B$4 -> 0.017031484 | P37: =J37/$B$4 -> 0.015684547 | Q37: =K37/$B$4 -> 0.014817227 | R37: =L37/$B$4 -> 0.014452349 | S37: =AVERAGE(N37:R37) -> 0.016845682 | U37: =U$3*$S37 -> 167.58996 | V37: =V$3*$S37 -> 174.19502 | W37: =W$3*$S37 -> 183.09351 | X37: =X$3*$S37 -> 190.84243 | Y37: =Y$3*$S37 -> 197.80614
A38: Total Non-Current Assets | B38: =SUM(B31,B32,B33,B34,B36,B37) -> 12473.49 | C38: =SUM(C31,C32,C33,C34,C36,C37) -> 10881.46 | D38: =SUM(D31,D32,D33,D34,D36,D37) -> 10246.09 | E38: =SUM(E31,E32,E33,E34,E36,E37) -> 9476.41 | F38: =SUM(F31,F32,F33,F34,F36,F37) -> 9672.02 | H38: =SUM(H31:H37) -> 11932.628 | I38: =SUM(I31:I37) -> 10467.318 | J38: =SUM(J31:J37) -> 9864.7 | K38: =SUM(K31:K37) -> 9116.11 | L38: =SUM(L31:L37) -> 9320.5925 | U38: =SUM(U31:U37) -> 12446.087 | V38: =SUM(V31:V37) -> 12936.612 | W38: =SUM(W31:W37) -> 13597.46 | X38: =SUM(X31:X37) -> 14172.934 | Y38: =SUM(Y31:Y37) -> 14690.095
A39: Total Assets
A40: Total Assets | B40: =B29+B38 -> 15755.23 | C40: =C29+C38 -> 13842.79 | D40: =D29+D38 -> 13565.05 | E40: =E29+E38 -> 12727.28 | F40: =F29+F38 -> 12911.6 | H40: =H29+H38 -> 15214.368 | I40: =I29+I38 -> 13428.648 | J40: =J29+J38 -> 13183.66 | K40: =K29+K38 -> 12366.98 | L40: =L29+L38 -> 12560.173
A41: Current Liabilities
A42: Trade Accounts Payable & Accruals - Short-Term | B42: 680.4 | C42: 598.41 | D42: 571.97 | E42: 527.8 | F42: 621.85 | H42: 680.4 | I42: 598.41 | J42: 571.97 | K42: 527.8 | L42: 621.85 | N42: =H42/$B$4 -> 0.083943727 | O42: =I42/$B$4 -> 0.073828285 | P42: =J42/$B$4 -> 0.070566275 | Q42: =K42/$B$4 -> 0.065116841 | R42: =L42/$B$4 -> 0.076720174 | S42: =AVERAGE(N42:R42) -> 0.07403506 | U42: =U$3*$S42 -> 736.54082 | V42: =V$3*$S42 -> 765.5694 | W42: =W$3*$S42 -> 804.67736 | X42: =X$3*$S42 -> 838.73308 | Y42: =Y$3*$S42 -> 869.33786
A43: Short-Term Debt & Current Portion of Long-Term Debt | B43: 661.03 | C43: 346.79 | D43: 341.86 | E43: 551.43 | F43: 663.12 | H43: 661.03 | I43: 346.79 | J43: 341.86 | K43: 551.43 | L43: 663.12 | N43: =H43/$B$4 -> 0.081553971 | O43: =I43/$B$4 -> 0.042784899 | P43: =J43/$B$4 -> 0.042176664 | Q43: =K43/$B$4 -> 0.068032171 | R43: =L43/$B$4 -> 0.081811822 | S43: =AVERAGE(N43:R43) -> 0.063271905 | U43: =U$3*$S43 -> 629.46314 | V43: =V$3*$S43 -> 654.27156 | W43: =W$3*$S43 -> 687.69404 | X43: =X$3*$S43 -> 716.79876 | Y43: =Y$3*$S43 -> 742.95425
A44: Income Taxes - Payable - Short-Term | B44: 27.49 | C44: 220.61 | D44: 374.26 | E44: 254.73 | F44: 145.16 | H44: 27.49 | I44: 220.61 | J44: 374.26 | K44: 254.73 | L44: 145.16 | N44: =H44/$B$4 -> 0.0033915536 | O44: =I44/$B$4 -> 0.027217557 | P44: =J44/$B$4 -> 0.046173985 | Q44: =K44/$B$4 -> 0.03142708 | R44: =L44/$B$4 -> 0.017908982 | S44: =AVERAGE(N44:R44) -> 0.025223831 | U44: =U$3*$S44 -> 250.94032 | V44: =V$3*$S44 -> 260.83039 | W44: =W$3*$S44 -> 274.15452 | X44: =X$3*$S44 -> 285.75734 | Y44: =Y$3*$S44 -> 296.18442
A45: Other Current Liabilities | B45: 952.89 | C45: 712.42 | D45: 796.12 | E45: 883.73 | F45: 640 | H45: 952.89 | I45: 712.42 | J45: 796.12 | K45: 883.73 | L45: 640 | N45: =H45/$B$4 -> 0.11756193 | O45: =I45/$B$4 -> 0.087894165 | P45: =J45/$B$4 -> 0.098220576 | Q45: =K45/$B$4 -> 0.10902938 | R45: =L45/$B$4 -> 0.078959414 | S45: =AVERAGE(N45:R45) -> 0.098333093 | U45: =U$3*$S45 -> 978.27079 | V45: =V$3*$S45 -> 1016.8264 | W45: =W$3*$S45 -> 1068.7695 | X45: =X$3*$S45 -> 1114.0022 | Y45: =Y$3*$S45 -> 1154.6513
A46: Total Current Liabilities | B46: =SUM(B42:B45) -> 2321.81 | C46: =SUM(C42:C45) -> 1878.23 | D46: =SUM(D42:D45) -> 2084.21 | E46: =SUM(E42:E45) -> 2217.69 | F46: =SUM(F42:F45) -> 2070.13 | H46: =SUM(H42:H45) -> 2321.81 | I46: =SUM(I42:I45) -> 1878.23 | J46: =SUM(J42:J45) -> 2084.21 | K46: =SUM(K42:K45) -> 2217.69 | L46: =SUM(L42:L45) -> 2070.13 | U46: =SUM(U42:U45) -> 2595.2151 | V46: =SUM(V42:V45) -> 2697.4978 | W46: =SUM(W42:W45) -> 2835.2954 | X46: =SUM(X42:X45) -> 2955.2913 | Y46: =SUM(Y42:Y45) -> 3063.1278
A47: Non-Current Liabilities
A48: Debt - Long-Term - Total | B48: 3854.34 | C48: 2753.69 | D48: 2670.88 | E48: 2683.38 | F48: 3952.76 | H48: 3854.34 | I48: 2753.69 | J48: 2670.88 | K48: 2683.38 | L48: 3952.76 | N48: =H48/$B$4 -> 0.47552567 | O48: =I48/$B$4 -> 0.33973398 | P48: =J48/$B$4 -> 0.32951737 | Q48: =K48/$B$4 -> 0.33105955 | R48: =L48/$B$4 -> 0.48766814 | S48: =AVERAGE(N48:R48) -> 0.39270094 | U48: =U$3*$S48 -> 3906.8014 | V48: =V$3*$S48 -> 4060.7764 | W48: =W$3*$S48 -> 4268.215 | X48: =X$3*$S48 -> 4448.8553 | Y48: =Y$3*$S48 -> 4611.1909
A49: Deferred Tax - Liability - Long-Term | B49: 362.59 | C49: 332.73 | D49: 264.24 | E49: 190.51 | F49: 173.34 | H49: 0 | I49: 0 | J49: 0 | K49: 0 | L49: 0 | N49: =H49/$B$4 -> 0 | O49: =I49/$B$4 -> 0 | P49: =J49/$B$4 -> 0 | Q49: =K49/$B$4 -> 0 | R49: =L49/$B$4 -> 0 | S49: =AVERAGE(N49:R49) -> 0 | U49: =U$3*$S49 -> 0 | V49: =V$3*$S49 -> 0 | W49: =W$3*$S49 -> 0 | X49: =X$3*$S49 -> 0 | Y49: =Y$3*$S49 -> 0
A50: Post Employment Benefits - Pension & Other - Long-Term | B50: 120.43 | C50: 80.99 | D50: 78.36 | E50: 109.3 | F50: 143.6 | H50: 120.43 | I50: 80.99 | J50: 78.36 | K50: 109.3 | L50: 143.6 | N50: =H50/$B$4 -> 0.014857941 | O50: =I50/$B$4 -> 0.009992067 | P50: =J50/$B$4 -> 0.0096675932 | Q50: =K50/$B$4 -> 0.013484787 | R50: =L50/$B$4 -> 0.017716518 | S50: =AVERAGE(N50:R50) -> 0.013143781 | U50: =U$3*$S50 -> 130.76145 | V50: =V$3*$S50 -> 135.91502 | W50: =W$3*$S50 -> 142.85804 | X50: =X$3*$S50 -> 148.9041 | Y50: =Y$3*$S50 -> 154.33751
A51: Other Non-Current Liabilities | B51: 91.8 | C51: 47.01 | D51: 26.09 | E51: 55.53 | F51: 122.91 | H51: 91.8 | I51: 47.01 | J51: 26.09 | K51: 55.53 | L51: 122.91 | N51: =H51/$B$4 -> 0.011325741 | O51: =I51/$B$4 -> 0.0057998157 | P51: =J51/$B$4 -> 0.0032188298 | Q51: =K51/$B$4 -> 0.0068509629 | R51: =L51/$B$4 -> 0.015163909 | S51: =AVERAGE(N51:R51) -> 0.0084718516 | U51: =U$3*$S51 -> 84.282562 | V51: =V$3*$S51 -> 87.604309 | W51: =W$3*$S51 -> 92.079444 | X51: =X$3*$S51 -> 95.976448 | Y51: =Y$3*$S51 -> 99.478561
A52: Total Non-Current Liabilities | B52: =SUM(B48:B51) -> 4429.16 | C52: =SUM(C48:C51) -> 3214.42 | D52: =SUM(D48:D51) -> 3039.57 | E52: =SUM(E48:E51) -> 3038.72 | F52: =SUM(F48:F51) -> 4392.61 | H52: =SUM(H48:H51) -> 4066.57 | I52: =SUM(I48:I51) -> 2881.69 | J52: =SUM(J48:J51) -> 2775.33 | K52: =SUM(K48:K51) -> 2848.21 | L52: =SUM(L48:L51) -> 4219.27 | N52: =H52/$B$4 -> 0.50170935 | O52: =I52/$B$4 -> 0.35552586 | P52: =J52/$B$4 -> 0.3424038 | Q52: =K52/$B$4 -> 0.3513953 | R52: =L52/$B$4 -> 0.52054857 | S52: =AVERAGE(N52:R52) -> 0.41431658 | U52: =SUM(U48:U51) -> 4121.8454 | V52: =SUM(V48:V51) -> 4284.2957 | W52: =SUM(W48:W51) -> 4503.1525 | X52: =SUM(X48:X51) -> 4693.7358 | Y52: =SUM(Y48:Y51) -> 4865.007
A53: Total Liabilities
A54: Total Liabilities | B54: =SUM(B52,B46) -> 6750.97 | C54: =SUM(C52,C46) -> 5092.65 | D54: =SUM(D52,D46) -> 5123.78 | E54: =SUM(E52,E46) -> 5256.41 | F54: =SUM(F52,F46) -> 6462.74 | H54: =SUM(H46,H52) -> 6388.38 | I54: =SUM(I46,I52) -> 4759.92 | J54: =SUM(J46,J52) -> 4859.54 | K54: =SUM(K46,K52) -> 5065.9 | L54: =SUM(L46,L52) -> 6289.4 | U54: =SUM(U46,U52) -> 6717.0605 | V54: =SUM(V46,V52) -> 6981.7935 | W54: =SUM(W46,W52) -> 7338.4479 | X54: =SUM(X46,X52) -> 7649.0272 | Y54: =SUM(Y46,Y52) -> 7928.1348
A55: Net Assets | B55: =B40-B54 -> 9004.26 | C55: =C40-C54 -> 8750.14 | D55: =D40-D54 -> 8441.27 | E55: =E40-E54 -> 7470.87 | F55: =F40-F54 -> 6448.86 | H55: =H40-H54 -> 8825.9875 | I55: =I40-I54 -> 8668.7275 | J55: =J40-J54 -> 8324.12 | K55: =K40-K54 -> 7301.08 | L55: =L40-L54 -> 6270.7725
A56: Shareholders' Equity
A57: Retained Earnings - Total | B57: 3516.69 | C57: 3519.9 | D57: 3339.04 | E57: 2310.5 | F57: 1385.12 | H57: =B59+B51+B37-B39 -> 8730.57 | I57: =C59+C51+C37-C39 -> 8335.7 | J57: =D59+D51+D37-D39 -> 7807.75 | K57: =E59+E51+E37-E39 -> 6920.92 | L57: =F59+F51+F37-F39 -> 6165.23 | N57: =H57/$B$4 -> 1.0771261 | O57: =I57/$B$4 -> 1.0284094 | P57: =J57/$B$4 -> 0.963274 | Q57: =K57/$B$4 -> 0.85386216 | R57: =L57/$B$4 -> 0.7606296 | S57: =AVERAGE(N57:R57) -> 0.93666024 | U57: =U$3*$S57 -> 9318.4027 | V57: =V$3*$S57 -> 9685.6599 | W57: =W$3*$S57 -> 10180.437 | X57: =X$3*$S57 -> 10611.296 | Y57: =Y$3*$S57 -> 10998.495
A58: Comprehensive Income - Accumulated - Total | B58: 392.09 | C58: 480.95 | D58: 170.24 | E58: 74.14 | F58: 254.57 | H58: 392.09 | I58: 480.95 | J58: 170.24 | K58: 74.14 | L58: 254.57 | N58: =H58/$B$4 -> 0.048373745 | O58: =I58/$B$4 -> 0.059336766 | P58: =J58/$B$4 -> 0.021003204 | Q58: =K58/$B$4 -> 0.0091469546 | R58: =L58/$B$4 -> 0.031407341 | S58: =AVERAGE(N58:R58) -> 0.033853602 | U58: =U$3*$S58 -> 336.79394 | V58: =V$3*$S58 -> 350.06768 | W58: =W$3*$S58 -> 367.95036 | X58: =X$3*$S58 -> 383.52283 | Y58: =Y$3*$S58 -> 397.51731
A59: Common Equity - Total | B59: 7917.62 | C59: 7736.5 | D59: 7273.14 | E59: 6384.99 | F59: 5573.75 | H59: 7917.62 | I59: 7736.5 | J59: 7273.14 | K59: 6384.99 | L59: 5573.75 | N59: =H59/$B$4 -> 0.97682911 | O59: =I59/$B$4 -> 0.9544836 | P59: =J59/$B$4 -> 0.89731698 | Q59: =K59/$B$4 -> 0.78774229 | R59: =L59/$B$4 -> 0.6876563 | S59: =AVERAGE(N59:R59) -> 0.86080566 | U59: =U$3*$S59 -> 8563.7603 | V59: =V$3*$S59 -> 8901.2755 | W59: =W$3*$S59 -> 9355.9838 | X59: =X$3*$S59 -> 9751.9496 | Y59: =Y$3*$S59 -> 10107.791
A60: Minority Interest - Equity | B60: 157.5 | C60: 185.36 | D60: 155.03 | E60: 119.36 | F60: 90.65 | H60: 157.5 | I60: 185.36 | J60: 155.03 | K60: 119.36 | L60: 90.65 | N60: =H60/$B$4 -> 0.019431418 | O60: =I60/$B$4 -> 0.02286862 | P60: =J60/$B$4 -> 0.019126684 | Q60: =K60/$B$4 -> 0.014725931 | R60: =L60/$B$4 -> 0.011183861 | S60: =AVERAGE(N60:R60) -> 0.017467303 | U60: =U$3*$S60 -> 173.77418 | V60: =V$3*$S60 -> 180.62297 | W60: =W$3*$S60 -> 189.84982 | X60: =X$3*$S60 -> 197.88468 | Y60: =Y$3*$S60 -> 205.10536
A61: Total Shareholders' Equity
A62: Total Shareholders' Equity - including Minority Interest & Hybrid Debt | B62: =SUM(B59,B60) -> 8075.12 | C62: =SUM(C59,C60) -> 7921.86 | D62: =SUM(D59,D60) -> 7428.17 | E62: =SUM(E59,E60) -> 6504.35 | F62: =SUM(F59,F60) -> 5664.4 | H62: =H59+H60 -> 8075.12 | I62: =I59+I60 -> 7921.86 | J62: =J59+J60 -> 7428.17 | K62: =K59+K60 -> 6504.35 | L62: =L59+L60 -> 5664.4 | U62: =U60+U59 -> 8737.5344 | V62: =V60+V59 -> 9081.8985 | W62: =W60+W59 -> 9545.8336 | X62: =X60+X59 -> 9949.8343 | Y62: =Y60+Y59 -> 10312.897
A63: Total Liabilities & Shareholders' Equity
A64: Total Liabilities & Equity | B64: =SUM(B62,B54) -> 14826.09 | C64: =SUM(C62,C54) -> 13014.51 | D64: =SUM(D62,D54) -> 12551.95 | E64: =SUM(E62,E54) -> 11760.76 | F64: =SUM(F62,F54) -> 12127.14 | H64: =SUM(H62,H54) -> 14463.5 | I64: =SUM(I62,I54) -> 12681.78 | J64: =SUM(J62,J54) -> 12287.71 | K64: =SUM(K62,K54) -> 11570.25 | L64: =SUM(L62,L54) -> 11953.8 | U64: =SUM(U62,U54) -> 15454.595 | V64: =SUM(V62,V54) -> 16063.692 | W64: =SUM(W62,W54) -> 16884.282 | X64: =SUM(X62,X54) -> 17598.861 | Y64: =SUM(Y62,Y54) -> 18241.032
B67: 2025 F | C67: 2026 F | D67: 2027 F | E67: 2028 F | F67: 2029 F | N67: 2025 F | O67: 2026 F | P67: 2027 F | Q67: 2028 F | R67: 2029 F
A68: Valuation of FCFE | M68: Valuation of FCFE
A69: Earnings | B69: =U17 -> 1081.097 | C69: =V17 -> 1123.7052 | D69: =W17 -> 1181.108 | E69: =X17 -> 1231.0951 | F69: =Y17 -> 1276.0169 | M69: FCFE | N69: =B75 -> -1372.1616 | O69: =C75 -> 1067.7333 | P69: =D75 -> 1105.7013 | Q69: =E75 -> 1165.43 | R69: =F75 -> 1217.0057
A70: NCC | B70: =SUM(U6:U7) -> 348.7082 | C70: =SUM(V6:V7) -> 375.261 | D70: =SUM(W6:W7) -> 391.07981 | E70: =SUM(E6:E7) -> 641.59 | F70: =SUM(F6:F7) -> 605.87 | M70: D/E | N70: =U48/(U59+U60) -> 0.44712858 | O70: =V48/(V59+V60) -> 0.44712858 | P70: =W48/(W59+W60) -> 0.44712858 | Q70: =X48/(X59+X60) -> 0.44712858 | R70: =Y48/(Y59+Y60) -> 0.44712858
A71: WCInv | B71: =(U29-(U46-U43))-(H29-(H46-H43)) -> 1979.7819 | C71: =(V29-(V46-V43))-(U29-(U46-U43)) -> 141.91258 | D71: =(W29-(W46-W43))-(V29-(V46-V43)) -> 191.18788 | E71: =(X29-(X46-X43))-(W29-(W46-W43)) -> 166.48886 | F71: =(Y29-(Y46-Y43))-(X29-(X46-X43)) -> 149.61821 | M71: Unlevered beta | N71: =0.490965 -> 0.490965 | O71: =0.490965 -> 0.490965 | P71: =0.490965 -> 0.490965 | Q71: =0.490965 -> 0.490965 | R71: =0.490965 -> 0.490965
A72: FCInv | B72: =U38-H38+B70 -> 862.16753 | C72: =V38-U38+C70 -> 865.78663 | D72: =W38-V38+D70 -> 1051.9272 | E72: =X38-W38+E70 -> 1217.0644 | F72: =Y38-X38+F70 -> 1123.0304 | M72: Beta | N72: ='Beta & Cost of Equity'!I24 -> 0.741 | O72: ='Beta & Cost of Equity'!I24 -> 0.741 | P72: ='Beta & Cost of Equity'!I24 -> 0.741 | Q72: ='Beta & Cost of Equity'!I24 -> 0.741 | R72: ='Beta & Cost of Equity'!I24 -> 0.741
A73: Net Borrowing | B73: =(U43+U48)-(H43+H48) -> 20.894512 | C73: =(V43+V48)-(U43+U48) -> 178.78343 | D73: =(W43+W48)-(V43+V48) -> 240.86113 | E73: =(X43+X48)-(W43+W48) -> 209.74497 | F73: =(Y43+Y48)-(X43+X48) -> 188.4911 | M73: Risk-free rate | N73: =4.292% -> 0.04292 | O73: =4.292% -> 0.04292 | P73: =4.292% -> 0.04292 | Q73: =4.292% -> 0.04292 | R73: =4.292% -> 0.04292
A74: Other NCL | B74: =(U52-U48+U60)-(H52-H48+H60) -> 19.088184 | C74: =(V52-V46+V59)-(U52-U46+U59) -> 397.68285 | D74: =(W52-W46+W59)-(V52-V46+V59) -> 535.76746 | E74: =(X52-X46+X59)-(W52-W46+W59) -> 466.55319 | F74: =(Y52-Y46+Y59)-(X52-X46+X59) -> 419.27643 | M74: Risk premium | N74: =0.070176 -> 0.070176 | O74: =0.070176 -> 0.070176 | P74: =0.070176 -> 0.070176 | Q74: =0.070176 -> 0.070176 | R74: =0.070176 -> 0.070176
A75: FCFE | B75: =B69+B70-B71-B72+B73+B74 -> -1372.1616 | C75: =C69+C70-C71-C72+C73+C74 -> 1067.7333 | D75: =D69+D70-D71-D72+D73+D74 -> 1105.7013 | E75: =E69+E70-E71-E72+E73+E74 -> 1165.43 | F75: =F69+F70-F71-F72+F73+F74 -> 1217.0057 | M75: Cost of equity | N75: ='Beta & Cost of Equity'!V25 -> 0.0630011 | O75: =N75 -> 0.0630011 | P75: =O75 -> 0.0630011 | Q75: =P75 -> 0.0630011 | R75: =Q75 -> 0.0630011
M76: Present value | N76: =N69/(1+N75)^1 -> -1290.8374 | O76: =O69/(1+O75)^1 -> 1004.4517 | P76: =P69/(1+P75)^1 -> 1040.1695 | Q76: =Q69/(1+Q75)^1 -> 1096.3582 | R76: =R69/(1+R75)^1 -> 1144.8772
M77: Long-term growth rate | N77: 0.02 | O77: 0.02 | P77: 0.02 | Q77: 0.02 | R77: 0.02
M78: Terminal value | S78: =(R69*(1+R77)/(R75-R77)) -> 28867.77
M79: PVTV | S79: =S78/(1+R75)^5 -> 21268.882
M80: Total Present Value of Equity | S80: =SUM(N76:R76)+S79 -> 24263.901
M81: Number of Shares (m) | S81: 480.22
B82: 2025 F | C82: 2026 F | D82: 2027 F | E82: 2028 F | F82: 2029 F | M82: Price per Share ($) | S82: =S80/S81 -> 50.526637
A83: Valuation of FCFF | M83: Market Price as at 02/06/25 | S83: 26.25
A84: Earnings | B84: =U17 -> 1081.097 | C84: =V17 -> 1123.7052 | D84: =W17 -> 1181.108 | E84: =X17 -> 1231.0951 | F84: =Y17 -> 1276.0169 | M84: Reccommenation buy/ sell/ hold | S84: SELL
A85: NCC | B85: =B70 -> 348.7082 | C85: =C70 -> 375.261 | D85: =D70 -> 391.07981 | E85: =E70 -> 641.59 | F85: =F70 -> 605.87
A86: WCInv | B86: =B71 -> 1979.7819 | C86: =C71 -> 141.91258 | D86: =D71 -> 191.18788 | E86: =E71 -> 166.48886 | F86: =F71 -> 149.61821
A87: FCInv | B87: =B72 -> 862.16753 | C87: =C72 -> 865.78663 | D87: =D72 -> 1051.9272 | E87: =E72 -> 1217.0644 | F87: =F72 -> 1123.0304 | N87: 2025 F | O87: 2026 F | P87: 2027 F | Q87: 2028 F | R87: 2029 F
A88: Interest (1-T) | B88: =U11*(1-U15/U13) -> 94.124036 | C88: =V11*(1-V15/V13) -> 97.833656 | D88: =W11*(1-W15/W13) -> 102.83134 | E88: =X11*(1-X15/X13) -> 107.18339 | F88: =Y11*(1-Y15/Y13) -> 111.09444 | M88: Valuation of FCFF
A89: Other NCL | B89: =(U52-U48+U60)-(H52-H48+H60) -> 19.088184 | C89: =C74 -> 397.68285 | D89: =D74 -> 535.76746 | E89: =E74 -> 466.55319 | F89: =F74 -> 419.27643 | M89: FCFF | N89: =B90 -> -1298.9321 | O89: =C90 -> 986.7835 | P89: =D90 -> 967.67152 | Q89: =E90 -> 1062.8684 | R89: =F90 -> 1139.6091
A90: FCFF | B90: =B84+B85-B86-B87+B88+B89 -> -1298.9321 | C90: =C84+C85-C86-C87+C88+C89 -> 986.7835 | D90: =D84+D85-D86-D87+D88+D89 -> 967.67152 | E90: =E84+E85-E86-E87+E88+E89 -> 1062.8684 | F90: =F84+F85-F86-F87+F88+F89 -> 1139.6091 | M90: D/E | N90: =U48/(U59+U60) -> 0.44712858 | O90: =V48/(V59+V60) -> 0.44712858 | P90: =W48/(W59+W60) -> 0.44712858 | Q90: =X48/(X59+X60) -> 0.44712858 | R90: =Y48/(Y59+Y60) -> 0.44712858
M91: Unlevered Beta | N91: =N71 -> 0.490965 | O91: =O71 -> 0.490965 | P91: =P71 -> 0.490965 | Q91: =Q71 -> 0.490965 | R91: =R71 -> 0.490965
M92: Beta | N92: =N72 -> 0.741 | O92: =O72 -> 0.741 | P92: =P72 -> 0.741 | Q92: =Q72 -> 0.741 | R92: =R72 -> 0.741
M93: Risk-Free Rate | N93: =N73 -> 0.04292 | O93: =O73 -> 0.04292 | P93: =P73 -> 0.04292 | Q93: =Q73 -> 0.04292 | R93: =R73 -> 0.04292
M94: Risk Premium | N94: =N74 -> 0.070176 | O94: =O74 -> 0.070176 | P94: =P74 -> 0.070176 | Q94: =Q74 -> 0.070176 | R94: =R74 -> 0.070176
M95: Cost of Equity | N95: =N75 -> 0.0630011 | O95: =O75 -> 0.0630011 | P95: =P75 -> 0.0630011 | Q95: =Q75 -> 0.0630011 | R95: =R75 -> 0.0630011
M96: Cost of Debt | N96: ='Cost Of Debt & WACC'!B12 -> 0.032125464 | O96: =N96 -> 0.032125464 | P96: =O96 -> 0.032125464 | Q96: =P96 -> 0.032125464 | R96: =Q96 -> 0.032125464
M97: Long Term Growth Rate | N97: =N77 -> 0.02 | O97: =O77 -> 0.02 | P97: =P77 -> 0.02 | Q97: =Q77 -> 0.02 | R97: =R77 -> 0.02
M98: Effective Tax Rate | N98: =(U15/U13) -> 0.25105996 | O98: =(V15/V13) -> 0.25105996 | P98: =(W15/W13) -> 0.25105996 | Q98: =(X15/X13) -> 0.25105996 | R98: =(Y15/Y13) -> 0.25105996
M99: WACC | N99: ='Cost Of Debt & WACC'!B22 -> 0.0545 | O99: =N99 -> 0.0545 | P99: =O99 -> 0.0545 | Q99: =P99 -> 0.0545 | R99: =Q99 -> 0.0545
M100: Present Value | N100: =N89/(1+N99)^1 -> -1231.799 | O100: =O89/(1+O99)^1 -> 935.78331 | P100: =P89/(1+P99)^1 -> 917.6591 | Q100: =Q89/(1+Q99)^1 -> 1007.9359 | R100: =R89/(1+R99)^1 -> 1080.7104
M101: Total PV | S101: =SUM(N100:R100) -> 2710.2896
M102: Number of Shares (m) | S102: 480.22
M103: Price per Share ($) | S103: =S101/S102 -> 5.64385
...

Sheet Dividend Calculation
A1: Dividend calculation | G1: DPR=1-r
A2: Year | B2: Earnings | C2: RE (t-1) | D2: RE (t) | E2: Div Dist | F2: Retention Ratio | G2: Dividend payout ratio | H2: Assumed min 0% and max 100% as per instruction manual
A3: 2020 | B3: ='Income Sheet'!F20 -> 527.75 | C3: 1287 | D3: ='Income Sheet'!F57 -> 1385.12 | E3: =C3+B3-D3 -> 429.63 | F3: =1-G3 -> 0.18592136 | G3: =E3/B3 -> 0.81407864 | H3: 1
A4: 2021 | B4: ='Income Sheet'!E20 -> 1315.04 | C4: 1385.12 | D4: ='Income Sheet'!E57 -> 2310.5 | E4: =C4+B4-D4 -> 389.66 | F4: =1-G4 -> 0.70368962 | G4: =E4/B4 -> 0.29631038 | H4: 1
A5: 2022 | B5: ='Income Sheet'!D20 -> 1460.57 | C5: 2310.5 | D5: ='Income Sheet'!D57 -> 3339.04 | E5: =C5+B5-D5 -> 432.03 | F5: =1-G5 -> 0.70420452 | G5: =E5/B5 -> 0.29579548 | H5: 1
A6: 2023 | B6: ='Income Sheet'!C20 -> 684.98 | C6: 3339.04 | D6: 3519.9 | E6: =C6+B6-D6 -> 504.12 | F6: =1-G6 -> 0.26403691 | G6: =E6/B6 -> 0.73596309 | H6: 1
A7: 2024 | B7: ='Income Sheet'!B20 -> 511.09 | C7: 3519.9 | D7: ='Income Sheet'!B57 -> 3516.69 | E7: =C7+B7-D7 -> 514.3 | F7: =1-G7 -> -0.0062806942 | G7: =E7/B7 -> 1.0062807 | H7: 1 | I7: Average | J7: 1
A8: 2025 | B8: ='Income Sheet'!U20 -> 1117.1751 | C8: =D7 -> 3516.69 | D8: ='Income Sheet'!U57 -> 9318.4027 | E8: =B8*$J$7 -> 1117.1751 | F8: =1-G8 -> 0 | G8: =E8/B8 -> 1
A9: 2026 | B9: ='Income Sheet'!V20 -> 1161.2052 | C9: =D8 -> 9318.4027 | D9: ='Income Sheet'!V57 -> 9685.6599 | E9: =B9*$J$7 -> 1161.2052 | F9: =1-G9 -> 0 | G9: =E9/B9 -> 1
A10: 2027 | B10: ='Income Sheet'!W20 -> 1220.5236 | C10: =D9 -> 9685.6599 | D10: ='Income Sheet'!W57 -> 10180.437 | E10: =B10*$J$7 -> 1220.5236 | F10: =1-G10 -> 0 | G10: =E10/B10 -> 1
A11: 2028 | B11: ='Income Sheet'!X20 -> 1272.1789 | C11: =D10 -> 10180.437 | D11: ='Income Sheet'!X57 -> 10611.296 | E11: =B11*$J$7 -> 1272.1789 | F11: =1-G11 -> 0 | G11: =E11/B11 -> 1
A12: 2029 | B12: ='Income Sheet'!Y20 -> 1318.5998 | C12: =D11 -> 10611.296 | D12: ='Income Sheet'!Y57 -> 10998.495 | E12: =B12*$J$7 -> 1318.5998 | F12: =1-G12 -> 0 | G12: =E12/B12 -> 1

Sheet Section B
C3: Market Capitalisation
C4: Company | D4: ASX Code | E4: Market Capitalisation (AUD)
C5: Sonic Healthcare Ltd | D5: SHL | E5: 12820000000
C6: Ramsay Healthcare Ltd | D6: RHC | E6: 8730000000
C7: Healius Ltd | D7: HLS | E7: 635370000
C8: Mean | E8: =AVERAGE(E5:E7) -> 7.3951233e+09
C9: Median | E9: =MEDIAN(E5:E7) -> 8730000000
C10: As at 02/06/2025
C13: Peer Ratios (Outputs)
C14: Company | D14: ASX Code | E14: Trailing P/E Ratio | F14: Leading P/E Ratio | G14: PEG Ratio | H14: P/B Ratio
C15: Sonic Healthcare Ltd | D15: SHL | E15: 23.45 | F15: 21.28 | G15: =E15*((1-(G27))*H27) -> 0 | H15: 1.56
C16: Ramsay Healthcare Ltd | D16: RHC | E16: 489 | F16: 26.04 | G16: =E16*((1-(G28))*H28) -> 0.457704 | H16: 1.91
C17: Healius Ltd | D17: HLS | E17: 60.94 | F17: 78.74 | G17: =E17*((1-(G29))*H29) -> -1.1017708 | H17: 0.62
C18: Mean | E18: =AVERAGE(E15:E17) -> 191.13 | F18: =AVERAGE(F15:F17) -> 42.02 | G18: =AVERAGE(G15:G17) -> -0.21468894 | H18: =AVERAGE(H15:H17) -> 1.3633333
C19: Median | E19: =MEDIAN(E15:E17) -> 60.94 | F19: =MEDIAN(F15:F17) -> 26.04 | G19: =MEDIAN(G15:G17) -> 0 | H19: =MEDIAN(H15:H17) -> 1.56
C20: Sonic Healthcare Limited - Relative Valuation | E20: Overvalued | F20: Overvalued | G20: Overvalued | H20: Overvalued
C21: Formula Description | E21: P / EPS | F21: P / Forecasted EPS | G21: Trailing P/E/ g B = 1-DPR g = B x ROE Thus, Trailing P/E Ratio * g | H21: P / BVPS
C22: As at 02/06/2025
C25: Peer Ratios (Inputs) - For Appendix
C26: Company | D26: ASX Code | E26: EPS | F26: Forecasted EPS (2024) | G26: Dividend Payout Ratio | H26: ROE | I26: Equity | J26: Outstanding Shares | K26: Book Value Per Share
C27: Sonic Healthcare Ltd | D27: SHL | E27: 1.07 | F27: 1.091 | G27: ='Dividend Calculation'!G8 -> 1 | H27: 0.0716 | I27: 7917623 | J27: 480400000 | K27: 17.07
C28: Ramsay Healthcare Ltd | D28: RHC | E28: 3.89 | F28: 1.242 | G28: 0.82 | H28: 0.0052 | I28: 4897600 | J28: 230840000 | K28: 19.92
C29: Healius Ltd | D29: HLS | E29: -0.98 | F29: -0.02 | G29: 0.413 | H29: -0.0308 | I29: 1040700 | J29: 726130000 | K29: 1.41
C30: As at 02/06/2025
C31: Source: Refinitiv Workspace & Yahoo finance
C36: Fundamental Ratios (Inputs) - For Appendix
C37: Company | D37: ASX Code | E37: EPS | F37: Forecasted EPS (2024) | G37: Dividend Payout Ratio | H37: ROE | I37: Equity | J37: Outstanding Shares | K37: Book Value Per Share | L37: Cost of Equity | M37: Growth Rate (gh) | N37: Retention Ratio | O37: Sustainable Growth Rate (gs)
C38: Sonic Healthcare Ltd | D38: SHL | E38: =E27 -> 1.07 | F38: =F27 -> 1.091 | G38: =G27 -> 1 | H38: =H27 -> 0.0716 | I38: =I27 -> 7917623 | J38: =J27 -> 480400000 | K38: =K27 -> 17.07 | L38: 0.06 | M38: =((1-(G27))*H27) -> 0 | N38: =1-G38 -> 0 | O38: 0.03
C39: Ramsay Healthcare Ltd | D39: RHC | E39: =E28 -> 3.89 | F39: =F28 -> 1.242 | G39: =G28 -> 0.82 | H39: =H28 -> 0.0052 | I39: =I28 -> 4897600 | J39: =J28 -> 230840000 | K39: =K28 -> 19.92 | L39: 0.076 | M39: =((1-(G28))*H28) -> 0.000936 | N39: =1-G39 -> 0.18 | O39: 0.03
C40: Healius Ltd | D40: HLS | E40: =E29 -> -0.98 | F40: =F29 -> -0.02 | G40: =G29 -> 0.413 | H40: =H29 -> -0.0308 | I40: =I29 -> 1040700 | J40: =J29 -> 726130000 | K40: =K29 -> 1.41 | L40: 0.0787 | M40: =((1-(G29))*H29) -> -0.0180796 | N40: =1-G40 -> 0.587 | O40: 0.03
C41: As at 02/06/2025
C42: Source: Refinitiv Workspace & Yahoo finance
C46: Market Capitalisation
C47: Company | D47: ASX Code | E47: Market Capitalisation (AUD)
C48: Sonic Healthcare Ltd | D48: SHL | E48: =E5 -> 12820000000
C49: Ramsay Healthcare Ltd | D49: RHC | E49: =E6 -> 8730000000
C50: Healius Ltd | D50: HLS | E50: =E7 -> 635370000
C51: Mean | E51: =E8 -> 7.3951233e+09
C52: Median | E52: =E9 -> 8730000000
C53: As at 02/06/2025
C56: Peer Ratios (Outputs)
C57: Company | D57: ASX Code | E57: Trailing Fundamental PE | F57: 2 Stage Fundamental P/E Model **Assuming 3% Growth after 10 years | G57: Fundamental H Model
C58: Sonic Healthcare Ltd | D58: SHL | E58: =(((1-N38))*(1+M38)/(L38-M38)) -> 16.666667 | F58: =((1-N38)*(1+M38))*((1-((1+M38)/(1+L38))^10)/(L38-M38))+(((1-N38)*(1+M38)^10*(1+O38))/(L38-O38))*1/(1+L38)^10 -> 26.531641 | G58: =((1-N38)*((10/2)*(M38-O38)+(1+O38)))/(L38-O38) -> 29.333333
C59: Ramsay Healthcare Ltd | D59: RHC | E59: =(((1-N39))*(1+M39)/(L39-M39)) -> 10.934236 | F59: =((1-N39)*(1+M39))*((1-((1+M39)/(1+L39))^10)/(L39-M39))+(((1-N39)*(1+M39)^10*(1+O39))/(L39-O39))*1/(1+L39)^10 -> 14.537801 | G59: =((1-N39)*((10/2)*(M39-O39)+(1+O39)))/(L39-O39) -> 15.770383
C60: Healius Ltd | D60: HLS | E60: =(((1-N40))*(1+M40)/(L40-M40)) -> 4.1902749 | F60: =((1-N40)*(1+M40))*((1-((1+M40)/(1+L40))^10)/(L40-M40))+(((1-N40)*(1+M40)^10*(1+O40))/(L40-O40))*1/(1+L40)^10 -> 5.9655057 | G60: =((1-N40)*((10/2)*(M40-O40)+(1+O40)))/(L40-O40) -> 6.6962141
C61: Mean | E61: =AVERAGE(E58:E60) -> 10.597059 | F61: =AVERAGE(F58:F60) -> 15.678316 | G61: =AVERAGE(G58:G60) -> 17.266643
C62: Median | E62: =MEDIAN(E58:E60) -> 10.934236 | F62: =MEDIAN(F58:F60) -> 14.537801 | G62: =MEDIAN(G58:G60) -> 15.770383
C63: Sonic Healthcare Ltd - Relative Valuation | E63: Overvalued | F63: Overvalued | G63: Overvalued
C64: Formula Description | E64: ((1-b)(1+g))/(re-g) re = cost of equity B = 1-DPR g = B x ROE | F64: ((1-b)(1+gh))((1-((1+gh)/(1+re))^n)/(re-gh))+((1-b)(1+gh)^n(1+gs))/(re-gs)+1/(1+re)^n | G64: (DPS0*H(gh-gs)+DPS0(1+gs)/(re-gs)
C65: As at 02/06/2025

Sheet Regression
A1: Year | B1: Nominal Operating Revenue | C1: CPI | D1: Real Operating Revenue | I1: Real GDP ($ million) | J1: Real Operating Revenue
A2: 2000 | B2: 387.6 | C2: 71.475 | D2: =B2*$C$26/C2 -> 752.01721 | I2: 1037818 | J2: =D2 -> 752.01721
A3: 2001 | B3: 625.8 | C3: 74.625 | D3: =B3*$C$26/C3 -> 1162.9188 | I3: 1416147 | J3: =D3 -> 1162.9188
A4: 2002 | B4: 855.8 | C4: 76.85 | D4: =B4*$C$26/C4 -> 1544.2819 | I4: 1475047 | J4: =D4 -> 1544.2819 | M4: SUMMARY OUTPUT
A5: 2003 | B5: 972.1 | C5: 78.95 | D5: =B5*$C$26/C5 -> 1707.4853 | I5: 1519528 | J5: =D5 -> 1707.4853
A6: 2004 | B6: 1032.4 | C6: 80.8 | D6: =B6*$C$26/C6 -> 1771.8821 | I6: 1582030 | J6: =D6 -> 1771.8821 | M6: Regression Statistics
A7: 2005 | B7: 1380.5 | C7: 82.975 | D7: =B7*$C$26/C7 -> 2307.2111 | I7: 1629954 | J7: =D7 -> 2307.2111 | M7: Multiple R | N7: 0.95895076
A8: 2006 | B8: 1651.7 | C8: 85.925 | D8: =B8*$C$26/C8 -> 2665.691 | I8: 1672660 | J8: =D8 -> 2665.691 | M8: R Square | N8: 0.91958656
A9: 2007 | B9: 1886.1 | C9: 87.925 | D9: =B9*$C$26/C9 -> 2974.7503 | I9: 1745241 | J9: =D9 -> 2974.7503 | M9: Adjusted R Square | N9: 0.91609032
A10: 2008 | B10: 2378.9 | C10: 91.75 | D10: =B10*$C$26/C10 -> 3595.5745 | I10: 1790517 | J10: =D10 -> 3595.5745 | M10: Standard Error | N10: 815.10067
A11: 2009 | B11: 3013.5 | C11: 93.375 | D11: =B11*$C$26/C11 -> 4475.4711 | I11: 1825693 | J11: =D11 -> 4475.4711 | M11: Observations | N11: 25
A12: 2010 | B12: 2989.4 | C12: 96.1 | D12: =B12*$C$26/C12 -> 4313.7882 | I12: 1869858 | J12: =D12 -> 4313.7882
A13: 2011 | B13: 3096.2 | C13: 99.275 | D13: =B13*$C$26/C13 -> 4325.0117 | I13: 1921941 | J13: =D13 -> 4325.0117 | M13: ANOVA
A14: 2012 | B14: 3345.6 | C14: 101.025 | D14: =B14*$C$26/C14 -> 4592.4383 | I14: 1994764 | J14: =D14 -> 4592.4383 | N14: df | O14: SS | P14: MS | Q14: F | R14: Significance F
A15: 2013 | B15: 3484.1 | C15: 103.5 | D15: =B15*$C$26/C15 -> 4668.1891 | I15: 2039027 | J15: =D15 -> 4668.1891 | M15: Regression | N15: 1 | O15: 1.7474884e+08 | P15: 1.7474884e+08 | Q15: 263.02184 | R15: 4.4089269e-14
A16: 2014 | B16: 3913.5 | C16: 106.075 | D16: =B16*$C$26/C16 -> 5116.2349 | I16: 2091528 | J16: =D16 -> 5116.2349 | M16: Residual | N16: 23 | O16: 15280949 | P16: 664389.1
A17: 2015 | B17: 4200.5 | C17: 107.675 | D17: =B17*$C$26/C17 -> 5409.8383 | I17: 2140476 | J17: =D17 -> 5409.8383 | M17: Total | N17: 24 | O17: 1.9002979e+08
A18: 2016 | B18: 5017.7 | C18: 109.05 | D18: =B18*$C$26/C18 -> 6380.8303 | I18: 2198144 | J18: =D18 -> 6380.8303
A19: 2017 | B19: 5122.1 | C19: 111.175 | D19: =B19*$C$26/C19 -> 6389.0912 | I19: 2250465 | J19: =D19 -> 6389.0912 | N19: Coefficients | O19: Standard Error | P19: t Stat | Q19: P-value | R19: Lower 95% | S19: Upper 95% | T19: Lower 95.0% | U19: Upper 95.0%
A20: 2018 | B20: 5541.4 | C20: 113.3 | D20: =B20*$C$26/C20 -> 6782.4682 | I20: 2313275 | J20: =D20 -> 6782.4682 | M20: Intercept | N20: -8078.0726 | O20: 820.81867 | P20: -9.8414826 | Q20: 1.0325671e-09 | R20: -9776.0654 | S20: -6380.0799 | T20: -9776.0654 | U20: -6380.0799
A21: 2019 | B21: 6133.7 | C21: 115.125 | D21: =B21*$C$26/C21 -> 7388.4113 | E21: CPI Growth | G21: Taking the past 5 year average GDP | H21: GDP growth | I21: 2358070 | J21: =D21 -> 7388.4113 | M21: X Variable 1 | N21: 0.0066071064 | O21: 0.00040739471 | P21: 16.217948 | Q21: 4.4089269e-14 | R21: 0.0057643462 | S21: 0.0074498665 | T21: 0.0057643462 | U21: 0.0074498665
A22: 2020 | B22: 6831.8 | C22: 116.1 | D22: =B22*$C$26/C22 -> 8160.2056 | E22: =C22/C21-1 -> 0.0084690554 | H22: =I22/I21-1 -> -0.01954819 | I22: 2311974 | J22: =D22 -> 8160.2056
A23: 2021 | B23: 8754.1 | C23: 119.425 | D23: =B23*$C$26/C23 -> 10165.165 | E23: =C23/C22-1 -> 0.028639104 | H23: =I23/I22-1 -> 0.054115228 | I23: 2437087 | J23: =D23 -> 10165.165
A24: 2022 | B24: 9340.2 | C24: 127.3 | D24: =B24*$C$26/C24 -> 10174.802 | E24: =C24/C23-1 -> 0.065940967 | H24: =I24/I23-1 -> 0.041419941 | I24: 2538031 | J24: =D24 -> 10174.802
A25: 2023 | B25: 8169 | C25: 134.425 | D25: =B25*$C$26/C25 -> 8427.2723 | E25: =C25/C24-1 -> 0.055970149 | H25: =I25/I24-1 -> 0.020557275 | I25: 2590206 | J25: =D25 -> 8427.2723
A26: 2024 | B26: 8967.4 | C26: 138.675 | D26: =B26*$C$26/C26 -> 8967.4 | E26: =C26/C25-1 -> 0.031616143 | H26: =I26/I25-1 -> 0.010382572 | I26: 2617099 | J26: =D26 -> 8967.4 | K26: Inflation | L26: Nominal Operating Revenue
A27: 2025 | E27: =AVERAGE(E22:E26) -> 0.038127084 | H27: =AVERAGE(H21:H26) -> 0.021385365 | I27: =I26+(I26*H27) -> 2673066.6 | J27: =$N$20+($N$21*I27) -> 9583.1628 | K27: =E27 -> 0.038127084 | L27: =J27*(1+K27) -> 9948.5409
A28: 2026 | H28: =AVERAGE(H22:H27) -> 0.021385365 | I28: =I27+(I27*H28) -> 2730231.1 | J28: =$N$20+($N$21*I28) -> 9960.8548 | K28: =E27 -> 0.038127084 | L28: =J28*(1+K28) -> 10340.633
A29: 2027 | H29: =AVERAGE(H23:H28) -> 0.028207624 | I29: =I28+(I28*H29) -> 2807244.5 | J29: =$N$20+($N$21*I29) -> 10469.69 | K29: =E27 -> 0.038127084 | L29: =J29*(1+K29) -> 10868.869
A30: 2028 | H30: =AVERAGE(H24:H29) -> 0.02388969 | I30: =I29+(I29*H30) -> 2874308.7 | J30: =$N$20+($N$21*I30) -> 10912.79 | K30: =E27 -> 0.038127084 | L30: =J30*(1+K30) -> 11328.863
A31: 2029 | H31: =AVERAGE(H25:H30) -> 0.020967982 | I31: =I30+(I30*H31) -> 2934577.1 | J31: =$N$20+($N$21*I31) -> 11310.99 | K31: =E27 -> 0.038127084 | L31: =J31*(1+K31) -> 11742.246

Sheet Beta & Cost of Equity
A1: Beta Calculation | R1: Cost of Equity
B5: Date | C5: ASX All Ordinaries Index | D5: ASX All Ordinaries Index - Daily Price Returns | E5: SHL Share Price | F5: SHL - Daily Returns | R5: Date | S5: 10 Year Bond Yield (%)-Rf | T5: Year | U5: Historic ASX 200 Prices | V5: ASX Accumulation Index Returns (Rm)
B6: 43647 | C6: 69660.23 | E6: 27.14 | R6: 41641 | S6: 4.292 | T6: 2014 | U6: 46046.93
B7: 43648 | C7: 69760.82 | D7: =(C7/C6)-1 -> 0.001444009 | E7: 27.24 | F7: =(E7/E6)-1 -> 0.0036845984 | H7: Regression Statistics | R7: 41642 | S7: 4.292 | T7: 2015 | U7: 47788.21 | V7: =(U7/U6)-1 -> 0.037815333
B8: 43649 | C8: 70065.96 | D8: =(C8/C7)-1 -> 0.0043740885 | E8: 27.3 | F8: =(E8/E7)-1 -> 0.0022026432 | H8: Multiple R | I8: 0.49096495 | R8: 41645 | S8: 4.292 | T8: 2016 | U8: 53353.97 | V8: =(U8/U7)-1 -> 0.11646722
B9: 43650 | C9: 70384.08 | D9: =(C9/C8)-1 -> 0.0045402932 | E9: 27.36 | F9: =(E9/E8)-1 -> 0.0021978022 | H9: R Square | I9: 0.24104658 | R9: 41646 | S9: 4.292 | T9: 2017 | U9: 60007.77 | V9: =(U9/U8)-1 -> 0.12471049
B10: 43651 | C10: 70703.89 | D10: =(C10/C9)-1 -> 0.0045437832 | E10: 27.65 | F10: =(E10/E9)-1 -> 0.010599415 | H10: Adjusted R Square | I10: 0.24044567 | R10: 41647 | S10: 4.292 | T10: 2018 | U10: 57887.91 | V10: =(U10/U9)-1 -> -0.035326425
B11: 43654 | C11: 69934.44 | D11: =(C11/C10)-1 -> -0.010882711 | E11: 27.16 | F11: =(E11/E10)-1 -> -0.017721519 | H11: Standard Error | I11: 0.014326452 | R11: 41648 | S11: 4.292 | T11: 2019 | U11: 71813.87 | V11: =(U11/U10)-1 -> 0.24056768
B12: 43655 | C12: 69861.58 | D12: =(C12/C11)-1 -> -0.0010418329 | E12: 27.42 | F12: =(E12/E11)-1 -> 0.0095729013 | H12: Observations | I12: 1265 | R12: 41649 | S12: 4.292 | T12: 2020 | U12: 74424.55 | V12: =(U12/U11)-1 -> 0.036353423
B13: 43656 | C13: 70146.83 | D13: =(C13/C12)-1 -> 0.004083074 | E13: 27.57 | F13: =(E13/E12)-1 -> 0.0054704595 | R13: 41652 | S13: 4.292 | T13: 2021 | U13: 87626.08 | V13: =(U13/U12)-1 -> 0.17738139
B14: 43657 | C14: 70438.19 | D14: =(C14/C13)-1 -> 0.0041535733 | E14: 27.65 | F14: =(E14/E13)-1 -> 0.0029017048 | H14: ANOVA | R14: 41653 | S14: 4.292 | T14: 2022 | U14: 85033.52 | V14: =(U14/U13)-1 -> -0.029586625
B15: 43658 | C15: 70262 | D15: =(C15/C14)-1 -> -0.002501342 | E15: 27.62 | F15: =(E15/E14)-1 -> -0.001084991 | I15: df | J15: SS | K15: MS | L15: F | M15: Significance F | R15: 41654 | S15: 4.292 | T15: 2023 | U15: 86796.56 | V15: =(U15/U14)-1 -> 0.020733471
B16: 43661 | C16: 69821.01 | D16: =(C16/C15)-1 -> -0.0062763656 | E16: 27.66 | F16: =(E16/E15)-1 -> 0.0014482259 | H16: Regression | I16: 1 | J16: 0.082331587 | K16: 0.082331587 | L16: 401.13374 | M16: 1.0348514e-77 | R16: 41655 | S16: 4.292 | T16: 2024 | U16: 87894.32 | V16: =(U16/U15)-1 -> 0.012647506
B17: 43662 | C17: 69713.75 | D17: =(C17/C16)-1 -> -0.0015362138 | E17: 27.7 | F17: =(E17/E16)-1 -> 0.0014461316 | H17: Residual | I17: 1263 | J17: 0.25922724 | K17: 0.00020524722 | R17: 41656 | S17: 4.292
B18: 43663 | C18: 70005.77 | D18: =(C18/C17)-1 -> 0.0041888437 | E18: 27.9 | F18: =(E18/E17)-1 -> 0.0072202166 | H18: Total | I18: 1264 | J18: 0.34155883 | R18: 41659 | S18: 4.292 | V18: =AVERAGE(V7:V16) -> 0.070176346
B19: 43664 | C19: 69709.61 | D19: =(C19/C18)-1 -> -0.0042305084 | E19: 27.82 | F19: =(E19/E18)-1 -> -0.0028673835 | R19: 41660 | S19: 4.292 | U19: Cost Of Equity
B20: 43665 | C20: 70235.78 | D20: =(C20/C19)-1 -> 0.0075480267 | E20: 27.91 | F20: =(E20/E19)-1 -> 0.0032350827 | I20: Coefficients | J20: Standard Error | K20: t Stat | L20: P-value | M20: Lower 95% | N20: Upper 95% | O20: Lower 95.0% | P20: Upper 95.0% | R20: 41661 | S20: 4.292
B21: 43668 | C21: 70184 | D21: =(C21/C20)-1 -> -0.00073723108 | E21: 27.53 | F21: =(E21/E20)-1 -> -0.013615192 | H21: Intercept | I21: -0.00014633896 | J21: 0.00040300771 | K21: -0.36311701 | L21: 0.71657824 | M21: -0.00093697723 | N21: 0.00064429932 | O21: -0.00093697723 | P21: 0.00064429932 | R21: 41662 | S21: 4.292 | U21: Varible
B22: 43669 | C22: 70507.28 | D22: =(C22/C21)-1 -> 0.004606178 | E22: 27.52 | F22: =(E22/E21)-1 -> -0.0003632401 | H22: Beta | I22: 0.74099268 | J22: 0.036997239 | K22: 20.028324 | L22: 1.0348514e-77 | M22: 0.66840986 | N22: 0.81357549 | O22: 0.66840986 | P22: 0.81357549 | R22: 41663 | S22: 4.292 | U22: Rm-Rf | V22: =2.71/100 -> 0.0271
B23: 43670 | C23: 71023.78 | D23: =(C23/C22)-1 -> 0.0073254847 | E23: 27.87 | F23: =(E23/E22)-1 -> 0.012718023 | R23: 41667 | S23: 4.292 | U23: Beta | V23: =I24 -> 0.741
B24: 43671 | C24: 71432.24 | D24: =(C24/C23)-1 -> 0.0057510316 | E24: 28.15 | F24: =(E24/E23)-1 -> 0.010046645 | H24: Beta | I24: 0.741 | R24: 41668 | S24: 4.292 | U24: Rf | V24: =4.292/100 -> 0.04292
B25: 43672 | C25: 71199.36 | D25: =(C25/C24)-1 -> -0.0032601526 | E25: 27.37 | F25: =(E25/E24)-1 -> -0.027708703 | R25: 41669 | S25: 4.292 | U25: Cost Of Equity | V25: =V24+(V23*V22) -> 0.0630011
B26: 43675 | C26: 71531.46 | D26: =(C26/C25)-1 -> 0.0046643678 | E26: 27.78 | F26: =(E26/E25)-1 -> 0.014979905 | R26: 41670 | S26: 4.292
B27: 43676 | C27: 71706.29 | D27: =(C27/C26)-1 -> 0.0024440994 | E27: 28 | F27: =(E27/E26)-1 -> 0.0079193665 | R27: 41673 | S27: 4.292
B28: 43677 | C28: 71378.47 | D28: =(C28/C27)-1 -> -0.0045717049 | E28: 28.04 | F28: =(E28/E27)-1 -> 0.0014285714 | R28: 41674 | S28: 4.292
B29: 43678 | C29: 71122.68 | D29: =(C29/C28)-1 -> -0.0035835736 | E29: 28.1 | F29: =(E29/E28)-1 -> 0.0021398003 | R29: 41675 | S29: 4.292
B30: 43679 | C30: 70854.82 | D30: =(C30/C29)-1 -> -0.0037661685 | E30: 28.34 | F30: =(E30/E29)-1 -> 0.0085409253 | R30: 41676 | S30: 4.292
B31: 43682 | C31: 69452.95 | D31: =(C31/C30)-1 -> -0.019785104 | E31: 27.99 | F31: =(E31/E30)-1 -> -0.012350035 | R31: 41677 | S31: 4.292
B32: 43683 | C32: 67754.3 | D32: =(C32/C31)-1 -> -0.024457564 | E32: 26.98 | F32: =(E32/E31)-1 -> -0.036084316 | R32: 41680 | S32: 4.292
B33: 43684 | C33: 68189.8 | D33: =(C33/C32)-1 -> 0.0064276363 | E33: 27.57 | F33: =(E33/E32)-1 -> 0.02186805 | R33: 41681 | S33: 4.292
B34: 43685 | C34: 68774.03 | D34: =(C34/C33)-1 -> 0.0085677037 | E34: 27.8 | F34: =(E34/E33)-1 -> 0.0083424012 | R34: 41682 | S34: 4.292
B35: 43686 | C35: 68994.27 | D35: =(C35/C34)-1 -> 0.0032023716 | E35: 27.7 | F35: =(E35/E34)-1 -> -0.0035971223 | R35: 41683 | S35: 4.292
B36: 43689 | C36: 69063.73 | D36: =(C36/C35)-1 -> 0.0010067503 | E36: 27.98 | F36: =(E36/E35)-1 -> 0.010108303 | R36: 41684 | S36: 4.292
B37: 43690 | C37: 68840.16 | D37: =(C37/C36)-1 -> -0.003237155 | E37: 28.13 | F37: =(E37/E36)-1 -> 0.0053609721 | R37: 41687 | S37: 4.292
... B1271: 45471 | C1271: 100125.06 | D1271: =(C1271/C1270)-1 -> 0.0014070198 | E1271: 26.3 | F1271: =(E1271/E1270)-1 -> -0.0026545317 | R1271: 43467 | S1271: 4.292
R1272: 43468 | S1272: 4.292
R1273: 43469 | S1273: 4.292
R1274: 43472 | S1274: 4.292
R1275: 43473 | S1275: 4.292
R1276: 43474 | S1276: 4.292
R1277: 43475 | S1277: 4.292
R1278: 43476 | S1278: 4.292
R1279: 43479 | S1279: 4.292
R1280: 43480 | S1280: 4.292
R1281: 43481 | S1281: 4.292
R1282: 43482 | S1282: 4.292
R1283: 43483 | S1283: 4.292
... R2789: 45657 | S2789: 4.292
S2791: =AVERAGE(S6:S2789) -> 4.292

Sheet Cost Of Debt & WACC
A2: Cost Of Debt Calculation | B2: 2024 | C2: 2023 | H2: Weight Calculation | I2: $ | J2: %
A3: Interest Expense | B3: 100.6 | H3: Total Debt | I3: 2987.9 | J3: =(I3/I5)*100 -> 27.398102
A4: Short Term Debt | B4: 297.5 | H4: Total Equity | I4: 7917.6 | J4: =(I4/I5)*100 -> 72.601898
A5: Long Term Debt | B5: 2690.4 | C5: 1673.5 | H5: Total Value | I5: 10905.5 | J5: 1
A6: Total Debt (FY2024) | B6: =B5+B4 -> 2987.9
A7: Average Debt (FY2024) | B7: =(B6+C5)/2 -> 2330.7
A8: Cost Of Debt Calculation | B8: =B3/B7 -> 0.043162998
A9: Income Tax Expense | B9: 186.84
A10: Income Before Tax | B10: 730.65
A11: Effective Tax Rate | B11: =B9/B10 -> 0.25571751
A12: Cost Of Debt *(1-t) | B12: =B8*(1-B11) -> 0.032125464
A15: Cost of Equity | B15: 0.063
A16: Cost of Debt | B16: 0.04
A17: Weight of Debt | B17: 27.3981
A18: Weight of Equity | B18: 72.6019
A20: The Weighted Average Cost Of Capital (WACC) is calculated as follows
A21: WACC=(Weight of Equity*Cost of Equity)+(Weight of Debt*After Tax Cost of Debt)
B22: =0.0545 -> 0.0545
